codersaoplay/__init__.py
codersaoplay/core.py
codersaoplay-0.2.dist-info/METADATA
codersaoplay-0.2.dist-info/WHEEL
codersaoplay-0.2.dist-info/top_level.txt
codersaoplay-0.2.dist-info/RECORD
